{"url": "https://api.github.com/repos/datalad/datalad/issues/1808", "repository_url": "https://api.github.com/repos/datalad/datalad", "labels_url": "https://api.github.com/repos/datalad/datalad/issues/1808/labels{/name}", "comments_url": "https://api.github.com/repos/datalad/datalad/issues/1808/comments", "events_url": "https://api.github.com/repos/datalad/datalad/issues/1808/events", "html_url": "https://github.com/datalad/datalad/pull/1808", "id": 256214091, "node_id": "MDExOlB1bGxSZXF1ZXN0MTQwMDA3Mzc4", "number": 1808, "title": "RF: Don't reinvent the wheel", "user": {"login": "bpoldrack", "id": 10498301, "node_id": "MDQ6VXNlcjEwNDk4MzAx", "avatar_url": "https://avatars.githubusercontent.com/u/10498301?v=4", "gravatar_id": "", "url": "https://api.github.com/users/bpoldrack", "html_url": "https://github.com/bpoldrack", "followers_url": "https://api.github.com/users/bpoldrack/followers", "following_url": "https://api.github.com/users/bpoldrack/following{/other_user}", "gists_url": "https://api.github.com/users/bpoldrack/gists{/gist_id}", "starred_url": "https://api.github.com/users/bpoldrack/starred{/owner}{/repo}", "subscriptions_url": "https://api.github.com/users/bpoldrack/subscriptions", "organizations_url": "https://api.github.com/users/bpoldrack/orgs", "repos_url": "https://api.github.com/users/bpoldrack/repos", "events_url": "https://api.github.com/users/bpoldrack/events{/privacy}", "received_events_url": "https://api.github.com/users/bpoldrack/received_events", "type": "User", "site_admin": false}, "labels": [], "state": "closed", "locked": false, "assignee": null, "assignees": [], "milestone": {"url": "https://api.github.com/repos/datalad/datalad/milestones/45", "html_url": "https://github.com/datalad/datalad/milestone/45", "labels_url": "https://api.github.com/repos/datalad/datalad/milestones/45/labels", "id": 2752976, "node_id": "MDk6TWlsZXN0b25lMjc1Mjk3Ng==", "number": 45, "title": "Release 0.9.0", "description": "", "creator": {"login": "yarikoptic", "id": 39889, "node_id": "MDQ6VXNlcjM5ODg5", "avatar_url": "https://avatars.githubusercontent.com/u/39889?v=4", "gravatar_id": "", "url": "https://api.github.com/users/yarikoptic", "html_url": "https://github.com/yarikoptic", "followers_url": "https://api.github.com/users/yarikoptic/followers", "following_url": "https://api.github.com/users/yarikoptic/following{/other_user}", "gists_url": "https://api.github.com/users/yarikoptic/gists{/gist_id}", "starred_url": "https://api.github.com/users/yarikoptic/starred{/owner}{/repo}", "subscriptions_url": "https://api.github.com/users/yarikoptic/subscriptions", "organizations_url": "https://api.github.com/users/yarikoptic/orgs", "repos_url": "https://api.github.com/users/yarikoptic/repos", "events_url": "https://api.github.com/users/yarikoptic/events{/privacy}", "received_events_url": "https://api.github.com/users/yarikoptic/received_events", "type": "User", "site_admin": false}, "open_issues": 0, "closed_issues": 8, "state": "closed", "created_at": "2017-09-08T13:31:08Z", "updated_at": "2017-09-25T18:54:29Z", "due_on": null, "closed_at": "2017-09-25T18:54:29Z"}, "comments": 1, "created_at": "2017-09-08T10:45:04Z", "updated_at": "2020-09-02T10:21:11Z", "closed_at": "2017-09-08T13:37:13Z", "author_association": "MEMBER", "active_lock_reason": null, "pull_request": {"url": "https://api.github.com/repos/datalad/datalad/pulls/1808", "html_url": "https://github.com/datalad/datalad/pull/1808", "diff_url": "https://github.com/datalad/datalad/pull/1808.diff", "patch_url": "https://github.com/datalad/datalad/pull/1808.patch"}, "body": "Just a minor change. Stumbled upon this one when looking at #1804 ", "closed_by": {"login": "yarikoptic", "id": 39889, "node_id": "MDQ6VXNlcjM5ODg5", "avatar_url": "https://avatars.githubusercontent.com/u/39889?v=4", "gravatar_id": "", "url": "https://api.github.com/users/yarikoptic", "html_url": "https://github.com/yarikoptic", "followers_url": "https://api.github.com/users/yarikoptic/followers", "following_url": "https://api.github.com/users/yarikoptic/following{/other_user}", "gists_url": "https://api.github.com/users/yarikoptic/gists{/gist_id}", "starred_url": "https://api.github.com/users/yarikoptic/starred{/owner}{/repo}", "subscriptions_url": "https://api.github.com/users/yarikoptic/subscriptions", "organizations_url": "https://api.github.com/users/yarikoptic/orgs", "repos_url": "https://api.github.com/users/yarikoptic/repos", "events_url": "https://api.github.com/users/yarikoptic/events{/privacy}", "received_events_url": "https://api.github.com/users/yarikoptic/received_events", "type": "User", "site_admin": false}, "reactions": {"url": "https://api.github.com/repos/datalad/datalad/issues/1808/reactions", "total_count": 0, "+1": 0, "-1": 0, "laugh": 0, "hooray": 0, "confused": 0, "heart": 0, "rocket": 0, "eyes": 0}, "timeline_url": "https://api.github.com/repos/datalad/datalad/issues/1808/timeline", "performed_via_github_app": null}