{"url": "https://api.github.com/repos/datalad/datalad/issues/2075", "repository_url": "https://api.github.com/repos/datalad/datalad", "labels_url": "https://api.github.com/repos/datalad/datalad/issues/2075/labels{/name}", "comments_url": "https://api.github.com/repos/datalad/datalad/issues/2075/comments", "events_url": "https://api.github.com/repos/datalad/datalad/issues/2075/events", "html_url": "https://github.com/datalad/datalad/issues/2075", "id": 288718788, "node_id": "MDU6SXNzdWUyODg3MTg3ODg=", "number": 2075, "title": "Why many \"bids:\" for majority of the fields but \"comment<participant#sex>\" ?", "user": {"login": "yarikoptic", "id": 39889, "node_id": "MDQ6VXNlcjM5ODg5", "avatar_url": "https://avatars.githubusercontent.com/u/39889?v=4", "gravatar_id": "", "url": "https://api.github.com/users/yarikoptic", "html_url": "https://github.com/yarikoptic", "followers_url": "https://api.github.com/users/yarikoptic/followers", "following_url": "https://api.github.com/users/yarikoptic/following{/other_user}", "gists_url": "https://api.github.com/users/yarikoptic/gists{/gist_id}", "starred_url": "https://api.github.com/users/yarikoptic/starred{/owner}{/repo}", "subscriptions_url": "https://api.github.com/users/yarikoptic/subscriptions", "organizations_url": "https://api.github.com/users/yarikoptic/orgs", "repos_url": "https://api.github.com/users/yarikoptic/repos", "events_url": "https://api.github.com/users/yarikoptic/events{/privacy}", "received_events_url": "https://api.github.com/users/yarikoptic/received_events", "type": "User", "site_admin": false}, "labels": [{"id": 63778594, "node_id": "MDU6TGFiZWw2Mzc3ODU5NA==", "url": "https://api.github.com/repos/datalad/datalad/labels/question", "name": "question", "color": "fbca04", "default": true, "description": "Issue asks a question rather than reporting a problem"}], "state": "closed", "locked": false, "assignee": null, "assignees": [], "milestone": null, "comments": 1, "created_at": "2018-01-15T21:18:40Z", "updated_at": "2018-01-16T18:43:00Z", "closed_at": "2018-01-16T18:43:00Z", "author_association": "MEMBER", "active_lock_reason": null, "body": "#### What is the problem?\r\n\r\n@mih - I just wonder what is the logic to decide between using `bids:` prefix vs the `comment`?  because BIDS does not prescribe the units (years vs months)?", "closed_by": {"login": "mih", "id": 136479, "node_id": "MDQ6VXNlcjEzNjQ3OQ==", "avatar_url": "https://avatars.githubusercontent.com/u/136479?v=4", "gravatar_id": "", "url": "https://api.github.com/users/mih", "html_url": "https://github.com/mih", "followers_url": "https://api.github.com/users/mih/followers", "following_url": "https://api.github.com/users/mih/following{/other_user}", "gists_url": "https://api.github.com/users/mih/gists{/gist_id}", "starred_url": "https://api.github.com/users/mih/starred{/owner}{/repo}", "subscriptions_url": "https://api.github.com/users/mih/subscriptions", "organizations_url": "https://api.github.com/users/mih/orgs", "repos_url": "https://api.github.com/users/mih/repos", "events_url": "https://api.github.com/users/mih/events{/privacy}", "received_events_url": "https://api.github.com/users/mih/received_events", "type": "User", "site_admin": false}, "reactions": {"url": "https://api.github.com/repos/datalad/datalad/issues/2075/reactions", "total_count": 0, "+1": 0, "-1": 0, "laugh": 0, "hooray": 0, "confused": 0, "heart": 0, "rocket": 0, "eyes": 0}, "timeline_url": "https://api.github.com/repos/datalad/datalad/issues/2075/timeline", "performed_via_github_app": null}