{"url": "https://api.github.com/repos/datalad/datalad/issues/2241", "repository_url": "https://api.github.com/repos/datalad/datalad", "labels_url": "https://api.github.com/repos/datalad/datalad/issues/2241/labels{/name}", "comments_url": "https://api.github.com/repos/datalad/datalad/issues/2241/comments", "events_url": "https://api.github.com/repos/datalad/datalad/issues/2241/events", "html_url": "https://github.com/datalad/datalad/pull/2241", "id": 300841069, "node_id": "MDExOlB1bGxSZXF1ZXN0MTcxODIwOTE4", "number": 2241, "title": "NF: crawl Stanford digital repository", "user": {"login": "overlake333", "id": 28018084, "node_id": "MDQ6VXNlcjI4MDE4MDg0", "avatar_url": "https://avatars.githubusercontent.com/u/28018084?v=4", "gravatar_id": "", "url": "https://api.github.com/users/overlake333", "html_url": "https://github.com/overlake333", "followers_url": "https://api.github.com/users/overlake333/followers", "following_url": "https://api.github.com/users/overlake333/following{/other_user}", "gists_url": "https://api.github.com/users/overlake333/gists{/gist_id}", "starred_url": "https://api.github.com/users/overlake333/starred{/owner}{/repo}", "subscriptions_url": "https://api.github.com/users/overlake333/subscriptions", "organizations_url": "https://api.github.com/users/overlake333/orgs", "repos_url": "https://api.github.com/users/overlake333/repos", "events_url": "https://api.github.com/users/overlake333/events{/privacy}", "received_events_url": "https://api.github.com/users/overlake333/received_events", "type": "User", "site_admin": false}, "labels": [], "state": "closed", "locked": false, "assignee": null, "assignees": [], "milestone": null, "comments": 2, "created_at": "2018-02-28T00:04:33Z", "updated_at": "2018-07-31T17:55:33Z", "closed_at": "2018-07-31T17:55:33Z", "author_association": "MEMBER", "active_lock_reason": null, "pull_request": {"url": "https://api.github.com/repos/datalad/datalad/pulls/2241", "html_url": "https://github.com/datalad/datalad/pull/2241", "diff_url": "https://github.com/datalad/datalad/pull/2241.diff", "patch_url": "https://github.com/datalad/datalad/pull/2241.patch"}, "body": "Crawl a dataset given an xml file from the Stanford digital repository. \r\n\r\nSee issue: https://github.com/datalad/datasets/issues/16\r\nThis pull request proposes\r\n\r\n### Changes\r\n- [ ] This change is complete\r\n\r\nPlease have a look @datalad/developers", "closed_by": {"login": "yarikoptic", "id": 39889, "node_id": "MDQ6VXNlcjM5ODg5", "avatar_url": "https://avatars.githubusercontent.com/u/39889?v=4", "gravatar_id": "", "url": "https://api.github.com/users/yarikoptic", "html_url": "https://github.com/yarikoptic", "followers_url": "https://api.github.com/users/yarikoptic/followers", "following_url": "https://api.github.com/users/yarikoptic/following{/other_user}", "gists_url": "https://api.github.com/users/yarikoptic/gists{/gist_id}", "starred_url": "https://api.github.com/users/yarikoptic/starred{/owner}{/repo}", "subscriptions_url": "https://api.github.com/users/yarikoptic/subscriptions", "organizations_url": "https://api.github.com/users/yarikoptic/orgs", "repos_url": "https://api.github.com/users/yarikoptic/repos", "events_url": "https://api.github.com/users/yarikoptic/events{/privacy}", "received_events_url": "https://api.github.com/users/yarikoptic/received_events", "type": "User", "site_admin": false}, "reactions": {"url": "https://api.github.com/repos/datalad/datalad/issues/2241/reactions", "total_count": 0, "+1": 0, "-1": 0, "laugh": 0, "hooray": 0, "confused": 0, "heart": 0, "rocket": 0, "eyes": 0}, "timeline_url": "https://api.github.com/repos/datalad/datalad/issues/2241/timeline", "performed_via_github_app": null}