{"url": "https://api.github.com/repos/datalad/datalad/issues/2301", "repository_url": "https://api.github.com/repos/datalad/datalad", "labels_url": "https://api.github.com/repos/datalad/datalad/issues/2301/labels{/name}", "comments_url": "https://api.github.com/repos/datalad/datalad/issues/2301/comments", "events_url": "https://api.github.com/repos/datalad/datalad/issues/2301/events", "html_url": "https://github.com/datalad/datalad/issues/2301", "id": 305151145, "node_id": "MDU6SXNzdWUzMDUxNTExNDU=", "number": 2301, "title": "test_basic_aggregate: json.decoder.JSONDecodeError: Extra data: line 1 column 166 (char 165)", "user": {"login": "yarikoptic", "id": 39889, "node_id": "MDQ6VXNlcjM5ODg5", "avatar_url": "https://avatars.githubusercontent.com/u/39889?v=4", "gravatar_id": "", "url": "https://api.github.com/users/yarikoptic", "html_url": "https://github.com/yarikoptic", "followers_url": "https://api.github.com/users/yarikoptic/followers", "following_url": "https://api.github.com/users/yarikoptic/following{/other_user}", "gists_url": "https://api.github.com/users/yarikoptic/gists{/gist_id}", "starred_url": "https://api.github.com/users/yarikoptic/starred{/owner}{/repo}", "subscriptions_url": "https://api.github.com/users/yarikoptic/subscriptions", "organizations_url": "https://api.github.com/users/yarikoptic/orgs", "repos_url": "https://api.github.com/users/yarikoptic/repos", "events_url": "https://api.github.com/users/yarikoptic/events{/privacy}", "received_events_url": "https://api.github.com/users/yarikoptic/received_events", "type": "User", "site_admin": false}, "labels": [{"id": 63778590, "node_id": "MDU6TGFiZWw2Mzc3ODU5MA==", "url": "https://api.github.com/repos/datalad/datalad/labels/severity-normal", "name": "severity-normal", "color": "ff8888", "default": false, "description": "standard severity"}, {"id": 884298512, "node_id": "MDU6TGFiZWw4ODQyOTg1MTI=", "url": "https://api.github.com/repos/datalad/datalad/labels/fails-on-travis", "name": "fails-on-travis", "color": "eda19a", "default": false, "description": ""}], "state": "closed", "locked": false, "assignee": {"login": "mih", "id": 136479, "node_id": "MDQ6VXNlcjEzNjQ3OQ==", "avatar_url": "https://avatars.githubusercontent.com/u/136479?v=4", "gravatar_id": "", "url": "https://api.github.com/users/mih", "html_url": "https://github.com/mih", "followers_url": "https://api.github.com/users/mih/followers", "following_url": "https://api.github.com/users/mih/following{/other_user}", "gists_url": "https://api.github.com/users/mih/gists{/gist_id}", "starred_url": "https://api.github.com/users/mih/starred{/owner}{/repo}", "subscriptions_url": "https://api.github.com/users/mih/subscriptions", "organizations_url": "https://api.github.com/users/mih/orgs", "repos_url": "https://api.github.com/users/mih/repos", "events_url": "https://api.github.com/users/mih/events{/privacy}", "received_events_url": "https://api.github.com/users/mih/received_events", "type": "User", "site_admin": false}, "assignees": [{"login": "mih", "id": 136479, "node_id": "MDQ6VXNlcjEzNjQ3OQ==", "avatar_url": "https://avatars.githubusercontent.com/u/136479?v=4", "gravatar_id": "", "url": "https://api.github.com/users/mih", "html_url": "https://github.com/mih", "followers_url": "https://api.github.com/users/mih/followers", "following_url": "https://api.github.com/users/mih/following{/other_user}", "gists_url": "https://api.github.com/users/mih/gists{/gist_id}", "starred_url": "https://api.github.com/users/mih/starred{/owner}{/repo}", "subscriptions_url": "https://api.github.com/users/mih/subscriptions", "organizations_url": "https://api.github.com/users/mih/orgs", "repos_url": "https://api.github.com/users/mih/repos", "events_url": "https://api.github.com/users/mih/events{/privacy}", "received_events_url": "https://api.github.com/users/mih/received_events", "type": "User", "site_admin": false}], "milestone": {"url": "https://api.github.com/repos/datalad/datalad/milestones/48", "html_url": "https://github.com/datalad/datalad/milestone/48", "labels_url": "https://api.github.com/repos/datalad/datalad/milestones/48/labels", "id": 3040617, "node_id": "MDk6TWlsZXN0b25lMzA0MDYxNw==", "number": 48, "title": "Release 0.10.0", "description": "The release with new metadata aggregation/search support.\r\n\r\nShould include 0.9.2 fixes etc, i.e. have 0.9.x branch merged", "creator": {"login": "yarikoptic", "id": 39889, "node_id": "MDQ6VXNlcjM5ODg5", "avatar_url": "https://avatars.githubusercontent.com/u/39889?v=4", "gravatar_id": "", "url": "https://api.github.com/users/yarikoptic", "html_url": "https://github.com/yarikoptic", "followers_url": "https://api.github.com/users/yarikoptic/followers", "following_url": "https://api.github.com/users/yarikoptic/following{/other_user}", "gists_url": "https://api.github.com/users/yarikoptic/gists{/gist_id}", "starred_url": "https://api.github.com/users/yarikoptic/starred{/owner}{/repo}", "subscriptions_url": "https://api.github.com/users/yarikoptic/subscriptions", "organizations_url": "https://api.github.com/users/yarikoptic/orgs", "repos_url": "https://api.github.com/users/yarikoptic/repos", "events_url": "https://api.github.com/users/yarikoptic/events{/privacy}", "received_events_url": "https://api.github.com/users/yarikoptic/received_events", "type": "User", "site_admin": false}, "open_issues": 0, "closed_issues": 51, "state": "closed", "created_at": "2018-01-16T22:43:30Z", "updated_at": "2018-06-13T16:50:07Z", "due_on": null, "closed_at": "2018-06-13T16:50:07Z"}, "comments": 4, "created_at": "2018-03-14T13:09:03Z", "updated_at": "2018-04-05T08:59:16Z", "closed_at": "2018-04-05T08:59:16Z", "author_association": "MEMBER", "active_lock_reason": null, "body": "#### What is the problem?\r\nHappened (or may be regularly) in that heavy debug mode matrix run (only):\r\nhttps://travis-ci.org/datalad/datalad/jobs/353137426\r\n\r\n```\r\n======================================================================\r\nERROR: datalad.metadata.tests.test_aggregation.test_basic_aggregate\r\n----------------------------------------------------------------------\r\nTraceback (most recent call last):\r\n  File \"/home/travis/virtualenv/python3.5.5/lib/python3.5/site-packages/nose/case.py\", line 198, in runTest\r\n    self.test(*self.arg)\r\n  File \"/home/travis/build/datalad/datalad/datalad/tests/utils.py\", line 494, in newfunc\r\n    return t(*(arg + (d,)), **kw)\r\n  File \"/home/travis/build/datalad/datalad/datalad/tests/utils.py\", line 905, in newfunc\r\n    return func(*args, **kwargs)\r\n  File \"/home/travis/build/datalad/datalad/datalad/tests/utils.py\", line 1057, in newfunc\r\n    return func(*args, **kwargs)\r\n  File \"/home/travis/build/datalad/datalad/datalad/metadata/tests/test_aggregation.py\", line 67, in test_basic_aggregate\r\n    base.aggregate_metadata(recursive=True)\r\n  File \"/home/travis/virtualenv/python3.5.5/lib/python3.5/site-packages/wrapt/wrappers.py\", line 562, in __call__\r\n    args, kwargs)\r\n  File \"/home/travis/build/datalad/datalad/datalad/distribution/dataset.py\", line 436, in apply_func\r\n    return f(**kwargs)\r\n  File \"/home/travis/virtualenv/python3.5.5/lib/python3.5/site-packages/wrapt/wrappers.py\", line 523, in __call__\r\n    args, kwargs)\r\n  File \"/home/travis/build/datalad/datalad/datalad/interface/utils.py\", line 470, in eval_func\r\n    return return_func(generator_func)(*args, **kwargs)\r\n  File \"/home/travis/virtualenv/python3.5.5/lib/python3.5/site-packages/wrapt/wrappers.py\", line 523, in __call__\r\n    args, kwargs)\r\n  File \"/home/travis/build/datalad/datalad/datalad/interface/utils.py\", line 458, in return_func\r\n    results = list(results)\r\n  File \"/home/travis/build/datalad/datalad/datalad/interface/utils.py\", line 414, in generator_func\r\n    result_renderer, result_xfm, _result_filter, **_kwargs):\r\n  File \"/home/travis/build/datalad/datalad/datalad/interface/utils.py\", line 482, in _process_results\r\n    for res in results:\r\n  File \"/home/travis/build/datalad/datalad/datalad/metadata/aggregate.py\", line 732, in __call__\r\n    to_save)\r\n  File \"/home/travis/build/datalad/datalad/datalad/metadata/aggregate.py\", line 472, in _update_ds_agginfo\r\n    save=False, result_renderer=None, return_type=list)\r\n  File \"/home/travis/virtualenv/python3.5.5/lib/python3.5/site-packages/wrapt/wrappers.py\", line 562, in __call__\r\n    args, kwargs)\r\n  File \"/home/travis/build/datalad/datalad/datalad/distribution/dataset.py\", line 436, in apply_func\r\n    return f(**kwargs)\r\n  File \"/home/travis/virtualenv/python3.5.5/lib/python3.5/site-packages/wrapt/wrappers.py\", line 523, in __call__\r\n    args, kwargs)\r\n  File \"/home/travis/build/datalad/datalad/datalad/interface/utils.py\", line 470, in eval_func\r\n    return return_func(generator_func)(*args, **kwargs)\r\n  File \"/home/travis/virtualenv/python3.5.5/lib/python3.5/site-packages/wrapt/wrappers.py\", line 523, in __call__\r\n    args, kwargs)\r\n  File \"/home/travis/build/datalad/datalad/datalad/interface/utils.py\", line 458, in return_func\r\n    results = list(results)\r\n  File \"/home/travis/build/datalad/datalad/datalad/interface/utils.py\", line 414, in generator_func\r\n    result_renderer, result_xfm, _result_filter, **_kwargs):\r\n  File \"/home/travis/build/datalad/datalad/datalad/interface/utils.py\", line 482, in _process_results\r\n    for res in results:\r\n  File \"/home/travis/build/datalad/datalad/datalad/distribution/add.py\", line 424, in __call__\r\n    **add_kw\r\n  File \"/home/travis/build/datalad/datalad/datalad/support/gitrepo.py\", line 300, in newfunc\r\n    result = func(self, files_new, *args, **kwargs)\r\n  File \"/home/travis/build/datalad/datalad/datalad/support/annexrepo.py\", line 1535, in add\r\n    expect_stderr=True\r\n  File \"/home/travis/build/datalad/datalad/datalad/support/annexrepo.py\", line 2394, in _run_annex_command_json\r\n    json_objects = [j for j in json_objects if 'byte-progress' not in j]\r\n  File \"/home/travis/build/datalad/datalad/datalad/support/annexrepo.py\", line 2394, in <listcomp>\r\n    json_objects = [j for j in json_objects if 'byte-progress' not in j]\r\n  File \"/home/travis/build/datalad/datalad/datalad/support/annexrepo.py\", line 2392, in <genexpr>\r\n    for line in out.splitlines() if line.startswith('{'))\r\n  File \"/opt/python/3.5.5/lib/python3.5/json/__init__.py\", line 319, in loads\r\n    return _default_decoder.decode(s)\r\n  File \"/opt/python/3.5.5/lib/python3.5/json/decoder.py\", line 342, in decode\r\n    raise JSONDecodeError(\"Extra data\", s, end)\r\njson.decoder.JSONDecodeError: Extra data: line 1 column 166 (char 165)\r\n-------------------- >> begin captured logging << --------------------\r\n```\r\n", "closed_by": {"login": "mih", "id": 136479, "node_id": "MDQ6VXNlcjEzNjQ3OQ==", "avatar_url": "https://avatars.githubusercontent.com/u/136479?v=4", "gravatar_id": "", "url": "https://api.github.com/users/mih", "html_url": "https://github.com/mih", "followers_url": "https://api.github.com/users/mih/followers", "following_url": "https://api.github.com/users/mih/following{/other_user}", "gists_url": "https://api.github.com/users/mih/gists{/gist_id}", "starred_url": "https://api.github.com/users/mih/starred{/owner}{/repo}", "subscriptions_url": "https://api.github.com/users/mih/subscriptions", "organizations_url": "https://api.github.com/users/mih/orgs", "repos_url": "https://api.github.com/users/mih/repos", "events_url": "https://api.github.com/users/mih/events{/privacy}", "received_events_url": "https://api.github.com/users/mih/received_events", "type": "User", "site_admin": false}, "reactions": {"url": "https://api.github.com/repos/datalad/datalad/issues/2301/reactions", "total_count": 0, "+1": 0, "-1": 0, "laugh": 0, "hooray": 0, "confused": 0, "heart": 0, "rocket": 0, "eyes": 0}, "timeline_url": "https://api.github.com/repos/datalad/datalad/issues/2301/timeline", "performed_via_github_app": null}