{"url": "https://api.github.com/repos/datalad/datalad/issues/3438", "repository_url": "https://api.github.com/repos/datalad/datalad", "labels_url": "https://api.github.com/repos/datalad/datalad/issues/3438/labels{/name}", "comments_url": "https://api.github.com/repos/datalad/datalad/issues/3438/comments", "events_url": "https://api.github.com/repos/datalad/datalad/issues/3438/events", "html_url": "https://github.com/datalad/datalad/issues/3438", "id": 446184178, "node_id": "MDU6SXNzdWU0NDYxODQxNzg=", "number": 3438, "title": "FOI: Debian isn't ready for development with python 3.8", "user": {"login": "yarikoptic", "id": 39889, "node_id": "MDQ6VXNlcjM5ODg5", "avatar_url": "https://avatars.githubusercontent.com/u/39889?v=4", "gravatar_id": "", "url": "https://api.github.com/users/yarikoptic", "html_url": "https://github.com/yarikoptic", "followers_url": "https://api.github.com/users/yarikoptic/followers", "following_url": "https://api.github.com/users/yarikoptic/following{/other_user}", "gists_url": "https://api.github.com/users/yarikoptic/gists{/gist_id}", "starred_url": "https://api.github.com/users/yarikoptic/starred{/owner}{/repo}", "subscriptions_url": "https://api.github.com/users/yarikoptic/subscriptions", "organizations_url": "https://api.github.com/users/yarikoptic/orgs", "repos_url": "https://api.github.com/users/yarikoptic/repos", "events_url": "https://api.github.com/users/yarikoptic/events{/privacy}", "received_events_url": "https://api.github.com/users/yarikoptic/received_events", "type": "User", "site_admin": false}, "labels": [], "state": "closed", "locked": false, "assignee": null, "assignees": [], "milestone": null, "comments": 1, "created_at": "2019-05-20T15:36:39Z", "updated_at": "2019-12-21T14:14:19Z", "closed_at": "2019-12-21T14:14:19Z", "author_association": "MEMBER", "active_lock_reason": null, "body": "3.8 is available from experimental but there seems to be a need for new virtualenv if to develop since existing one is incompatible.\r\n\r\n```\r\n$> virtualenv --system-site-packages --python=python3.8 venvs/dev3.8; source venvs/dev3.8/bin/activate             \r\nRunning virtualenv with interpreter /usr/bin/python3.8                                   \r\nTraceback (most recent call last):\r\n  File \"/usr/lib/python3/dist-packages/virtualenv.py\", line 25, in <module>\r\n    import distutils.sysconfig\r\nModuleNotFoundError: No module named 'distutils.sysconfig'\r\nsource: no such file or directory: venvs/dev3.8/bin/activate\r\n(dev) 1 13959 ->127 [1].....................................:Mon 20 May 2019 11:28:28 AM EDT:.\r\n(git)hopa:~datalad/datalad[0.11.x]git\r\n$> apt-cache policy python-virtualenv\r\npython-virtualenv:\r\n  Installed: 15.1.0+ds-2\r\n  Candidate: 15.1.0+ds-2\r\n  Version table:\r\n *** 15.1.0+ds-2 900\r\n        900 http://http.debian.net/debian buster/main amd64 Packages\r\n        900 http://http.debian.net/debian buster/main i386 Packages\r\n        600 http://http.debian.net/debian sid/main amd64 Packages\r\n        600 http://http.debian.net/debian sid/main i386 Packages\r\n        100 /var/lib/dpkg/status\r\n```\r\n\r\nAlso `venv` way also doesn't work for me :-/\r\n\r\n```\r\n$> dpkg -l python3.8{,-venv} | cat                                                        \r\nDesired=Unknown/Install/Remove/Purge/Hold\r\n| Status=Not/Inst/Conf-files/Unpacked/halF-conf/Half-inst/trig-aWait/Trig-pend\r\n|/ Err?=(none)/Reinst-required (Status,Err: uppercase=bad)\r\n||/ Name           Version      Architecture Description\r\n+++-==============-============-============-============================================================================\r\nii  python3.8      3.8.0~a4-3   amd64        Interactive high-level object-oriented language (version 3.8)\r\nii  python3.8-venv 3.8.0~a4-3   amd64        Interactive high-level object-oriented language (pyvenv binary, version 3.8)\r\nchanges on filesystem:                                                                                                     \r\n datalad/plugin/wtf.py | 15 +++++++++++++--\r\n1 13986 [1].....................................:Mon 20 May 2019 11:35:17 AM EDT:.\r\n(git)hopa:~datalad/datalad[0.11.x]git\r\n$> python3.8 -m venv venvs/dev3.8; source venvs/dev3.8/bin/activate\r\nThe virtual environment was not created successfully because ensurepip is not\r\navailable.  On Debian/Ubuntu systems, you need to install the python3-venv\r\npackage using the following command.\r\n\r\n    apt-get install python3-venv\r\n\r\nYou may need to use sudo with that command.  After installing the python3-venv\r\npackage, recreate your virtual environment.\r\n\r\nFailing command: ['/home/yoh/proj/datalad/datalad/venvs/dev3.8/bin/python3.8', '-Im', 'ensurepip', '--upgrade', '--default-pip']\r\n\r\nsource: no such file or directory: venvs/dev3.8/bin/activate\r\n\r\n```\r\n\r\nso if anyone has a good easy recipe to share how to get usable 3.8 env - please share", "closed_by": {"login": "mih", "id": 136479, "node_id": "MDQ6VXNlcjEzNjQ3OQ==", "avatar_url": "https://avatars.githubusercontent.com/u/136479?v=4", "gravatar_id": "", "url": "https://api.github.com/users/mih", "html_url": "https://github.com/mih", "followers_url": "https://api.github.com/users/mih/followers", "following_url": "https://api.github.com/users/mih/following{/other_user}", "gists_url": "https://api.github.com/users/mih/gists{/gist_id}", "starred_url": "https://api.github.com/users/mih/starred{/owner}{/repo}", "subscriptions_url": "https://api.github.com/users/mih/subscriptions", "organizations_url": "https://api.github.com/users/mih/orgs", "repos_url": "https://api.github.com/users/mih/repos", "events_url": "https://api.github.com/users/mih/events{/privacy}", "received_events_url": "https://api.github.com/users/mih/received_events", "type": "User", "site_admin": false}, "reactions": {"url": "https://api.github.com/repos/datalad/datalad/issues/3438/reactions", "total_count": 0, "+1": 0, "-1": 0, "laugh": 0, "hooray": 0, "confused": 0, "heart": 0, "rocket": 0, "eyes": 0}, "timeline_url": "https://api.github.com/repos/datalad/datalad/issues/3438/timeline", "performed_via_github_app": null}