{"url": "https://api.github.com/repos/datalad/datalad/issues/3652", "repository_url": "https://api.github.com/repos/datalad/datalad", "labels_url": "https://api.github.com/repos/datalad/datalad/issues/3652/labels{/name}", "comments_url": "https://api.github.com/repos/datalad/datalad/issues/3652/comments", "events_url": "https://api.github.com/repos/datalad/datalad/issues/3652/events", "html_url": "https://github.com/datalad/datalad/issues/3652", "id": 489852399, "node_id": "MDU6SXNzdWU0ODk4NTIzOTk=", "number": 3652, "title": "Different names to refer to procedures with run-procedures and create -c", "user": {"login": "adswa", "id": 29738718, "node_id": "MDQ6VXNlcjI5NzM4NzE4", "avatar_url": "https://avatars.githubusercontent.com/u/29738718?v=4", "gravatar_id": "", "url": "https://api.github.com/users/adswa", "html_url": "https://github.com/adswa", "followers_url": "https://api.github.com/users/adswa/followers", "following_url": "https://api.github.com/users/adswa/following{/other_user}", "gists_url": "https://api.github.com/users/adswa/gists{/gist_id}", "starred_url": "https://api.github.com/users/adswa/starred{/owner}{/repo}", "subscriptions_url": "https://api.github.com/users/adswa/subscriptions", "organizations_url": "https://api.github.com/users/adswa/orgs", "repos_url": "https://api.github.com/users/adswa/repos", "events_url": "https://api.github.com/users/adswa/events{/privacy}", "received_events_url": "https://api.github.com/users/adswa/received_events", "type": "User", "site_admin": false}, "labels": [], "state": "closed", "locked": false, "assignee": null, "assignees": [], "milestone": null, "comments": 3, "created_at": "2019-09-05T15:53:29Z", "updated_at": "2019-09-05T16:05:28Z", "closed_at": "2019-09-05T16:05:27Z", "author_association": "MEMBER", "active_lock_reason": null, "body": "This is remotely related to  #2649.\r\n\r\nI'm writing up a section on procedures, and found it confusing that ``datalad run-procedure`` uses the procedure name with a ``cfg`` prefix (e.g. ``datalad run-procedure cfg_yoda``) but when I apply the configuration template within ``create`` I need to call it without the prefix  (e.g. ``datalad create -c yoda someds``).\r\nWould it be useful to call the procedures in a uniform manner, or am I missing an obvious reason for this?", "closed_by": {"login": "adswa", "id": 29738718, "node_id": "MDQ6VXNlcjI5NzM4NzE4", "avatar_url": "https://avatars.githubusercontent.com/u/29738718?v=4", "gravatar_id": "", "url": "https://api.github.com/users/adswa", "html_url": "https://github.com/adswa", "followers_url": "https://api.github.com/users/adswa/followers", "following_url": "https://api.github.com/users/adswa/following{/other_user}", "gists_url": "https://api.github.com/users/adswa/gists{/gist_id}", "starred_url": "https://api.github.com/users/adswa/starred{/owner}{/repo}", "subscriptions_url": "https://api.github.com/users/adswa/subscriptions", "organizations_url": "https://api.github.com/users/adswa/orgs", "repos_url": "https://api.github.com/users/adswa/repos", "events_url": "https://api.github.com/users/adswa/events{/privacy}", "received_events_url": "https://api.github.com/users/adswa/received_events", "type": "User", "site_admin": false}, "reactions": {"url": "https://api.github.com/repos/datalad/datalad/issues/3652/reactions", "total_count": 0, "+1": 0, "-1": 0, "laugh": 0, "hooray": 0, "confused": 0, "heart": 0, "rocket": 0, "eyes": 0}, "timeline_url": "https://api.github.com/repos/datalad/datalad/issues/3652/timeline", "performed_via_github_app": null}