{"url": "https://api.github.com/repos/datalad/datalad/issues/3947", "repository_url": "https://api.github.com/repos/datalad/datalad", "labels_url": "https://api.github.com/repos/datalad/datalad/issues/3947/labels{/name}", "comments_url": "https://api.github.com/repos/datalad/datalad/issues/3947/comments", "events_url": "https://api.github.com/repos/datalad/datalad/issues/3947/events", "html_url": "https://github.com/datalad/datalad/issues/3947", "id": 539996326, "node_id": "MDU6SXNzdWU1Mzk5OTYzMjY=", "number": 3947, "title": "FOI: might soon need to remove my recent ENH for github authentication...", "user": {"login": "yarikoptic", "id": 39889, "node_id": "MDQ6VXNlcjM5ODg5", "avatar_url": "https://avatars.githubusercontent.com/u/39889?v=4", "gravatar_id": "", "url": "https://api.github.com/users/yarikoptic", "html_url": "https://github.com/yarikoptic", "followers_url": "https://api.github.com/users/yarikoptic/followers", "following_url": "https://api.github.com/users/yarikoptic/following{/other_user}", "gists_url": "https://api.github.com/users/yarikoptic/gists{/gist_id}", "starred_url": "https://api.github.com/users/yarikoptic/starred{/owner}{/repo}", "subscriptions_url": "https://api.github.com/users/yarikoptic/subscriptions", "organizations_url": "https://api.github.com/users/yarikoptic/orgs", "repos_url": "https://api.github.com/users/yarikoptic/repos", "events_url": "https://api.github.com/users/yarikoptic/events{/privacy}", "received_events_url": "https://api.github.com/users/yarikoptic/received_events", "type": "User", "site_admin": false}, "labels": [{"id": 1782622781, "node_id": "MDU6TGFiZWwxNzgyNjIyNzgx", "url": "https://api.github.com/repos/datalad/datalad/labels/severity-important", "name": "severity-important", "color": "cc0000", "default": false, "description": "major effect on the usability of a package, without rendering it completely unusable to everyone"}], "state": "closed", "locked": false, "assignee": {"login": "yarikoptic", "id": 39889, "node_id": "MDQ6VXNlcjM5ODg5", "avatar_url": "https://avatars.githubusercontent.com/u/39889?v=4", "gravatar_id": "", "url": "https://api.github.com/users/yarikoptic", "html_url": "https://github.com/yarikoptic", "followers_url": "https://api.github.com/users/yarikoptic/followers", "following_url": "https://api.github.com/users/yarikoptic/following{/other_user}", "gists_url": "https://api.github.com/users/yarikoptic/gists{/gist_id}", "starred_url": "https://api.github.com/users/yarikoptic/starred{/owner}{/repo}", "subscriptions_url": "https://api.github.com/users/yarikoptic/subscriptions", "organizations_url": "https://api.github.com/users/yarikoptic/orgs", "repos_url": "https://api.github.com/users/yarikoptic/repos", "events_url": "https://api.github.com/users/yarikoptic/events{/privacy}", "received_events_url": "https://api.github.com/users/yarikoptic/received_events", "type": "User", "site_admin": false}, "assignees": [{"login": "yarikoptic", "id": 39889, "node_id": "MDQ6VXNlcjM5ODg5", "avatar_url": "https://avatars.githubusercontent.com/u/39889?v=4", "gravatar_id": "", "url": "https://api.github.com/users/yarikoptic", "html_url": "https://github.com/yarikoptic", "followers_url": "https://api.github.com/users/yarikoptic/followers", "following_url": "https://api.github.com/users/yarikoptic/following{/other_user}", "gists_url": "https://api.github.com/users/yarikoptic/gists{/gist_id}", "starred_url": "https://api.github.com/users/yarikoptic/starred{/owner}{/repo}", "subscriptions_url": "https://api.github.com/users/yarikoptic/subscriptions", "organizations_url": "https://api.github.com/users/yarikoptic/orgs", "repos_url": "https://api.github.com/users/yarikoptic/repos", "events_url": "https://api.github.com/users/yarikoptic/events{/privacy}", "received_events_url": "https://api.github.com/users/yarikoptic/received_events", "type": "User", "site_admin": false}], "milestone": {"url": "https://api.github.com/repos/datalad/datalad/milestones/81", "html_url": "https://github.com/datalad/datalad/milestone/81", "labels_url": "https://api.github.com/repos/datalad/datalad/milestones/81/labels", "id": 6196851, "node_id": "MDk6TWlsZXN0b25lNjE5Njg1MQ==", "number": 81, "title": "0.13.6", "description": null, "creator": {"login": "yarikoptic", "id": 39889, "node_id": "MDQ6VXNlcjM5ODg5", "avatar_url": "https://avatars.githubusercontent.com/u/39889?v=4", "gravatar_id": "", "url": "https://api.github.com/users/yarikoptic", "html_url": "https://github.com/yarikoptic", "followers_url": "https://api.github.com/users/yarikoptic/followers", "following_url": "https://api.github.com/users/yarikoptic/following{/other_user}", "gists_url": "https://api.github.com/users/yarikoptic/gists{/gist_id}", "starred_url": "https://api.github.com/users/yarikoptic/starred{/owner}{/repo}", "subscriptions_url": "https://api.github.com/users/yarikoptic/subscriptions", "organizations_url": "https://api.github.com/users/yarikoptic/orgs", "repos_url": "https://api.github.com/users/yarikoptic/repos", "events_url": "https://api.github.com/users/yarikoptic/events{/privacy}", "received_events_url": "https://api.github.com/users/yarikoptic/received_events", "type": "User", "site_admin": false}, "open_issues": 0, "closed_issues": 28, "state": "closed", "created_at": "2020-12-09T17:06:54Z", "updated_at": "2021-01-03T22:14:17Z", "due_on": null, "closed_at": "2021-01-03T22:14:17Z"}, "comments": 2, "created_at": "2019-12-19T00:13:56Z", "updated_at": "2020-12-18T22:04:55Z", "closed_at": "2020-12-18T22:04:54Z", "author_association": "MEMBER", "active_lock_reason": null, "body": "Used create-sibling-github today and later received email:\r\n```shell\r\nDate: Wed, 18 Dec 2019 12:46:06 -0800                                                                                                                                                                                              \r\nFrom: GitHub <noreply@github.com>                                                                                                                                                                                                  \r\nTo: Yaroslav Halchenko <debian@onerussian.com>                                                                                                                                                                                     \r\nSubject: [GitHub] Deprecation Notice                                                                                                                                                                                               \r\n...                                                                                                                                                                                                                                   \r\n                                                                                                                                                                                      \r\nYou recently used a password to access an endpoint through the GitHub API using PyGithub/Python. We will deprecate basic authentication using password to this endpoint soon:                                                      \r\n                                                                                                                                                                                                                                   \r\nhttps://api.github.com/user                                                                                                                                                                                                        \r\n                                                                                                                                                                                                                                   \r\nWe recommend using a personal access token (PAT) with the appropriate scope to access this endpoint instead. Visit https://github.com/settings/tokens for more information.                                                        \r\n                                                                                                                                                                                                                                   \r\nThanks,                                                                                                                                                                                                                            \r\nThe GitHub Team \r\n```\r\nwhich is I guess due to us obtaining a token programmatically using https://pypi.python.org/pypi/PyGithub , not sure if there is anything it should do on its end I have [not spotted any related issue related to such an email in their issue tracker](https://github.com/PyGithub/PyGithub/search?q=endpoint+through+the+GitHub+API+using+PyGithub%2FPython&type=Issues)", "closed_by": {"login": "yarikoptic", "id": 39889, "node_id": "MDQ6VXNlcjM5ODg5", "avatar_url": "https://avatars.githubusercontent.com/u/39889?v=4", "gravatar_id": "", "url": "https://api.github.com/users/yarikoptic", "html_url": "https://github.com/yarikoptic", "followers_url": "https://api.github.com/users/yarikoptic/followers", "following_url": "https://api.github.com/users/yarikoptic/following{/other_user}", "gists_url": "https://api.github.com/users/yarikoptic/gists{/gist_id}", "starred_url": "https://api.github.com/users/yarikoptic/starred{/owner}{/repo}", "subscriptions_url": "https://api.github.com/users/yarikoptic/subscriptions", "organizations_url": "https://api.github.com/users/yarikoptic/orgs", "repos_url": "https://api.github.com/users/yarikoptic/repos", "events_url": "https://api.github.com/users/yarikoptic/events{/privacy}", "received_events_url": "https://api.github.com/users/yarikoptic/received_events", "type": "User", "site_admin": false}, "reactions": {"url": "https://api.github.com/repos/datalad/datalad/issues/3947/reactions", "total_count": 0, "+1": 0, "-1": 0, "laugh": 0, "hooray": 0, "confused": 0, "heart": 0, "rocket": 0, "eyes": 0}, "timeline_url": "https://api.github.com/repos/datalad/datalad/issues/3947/timeline", "performed_via_github_app": null}