{"url": "https://api.github.com/repos/datalad/datalad/issues/4063", "repository_url": "https://api.github.com/repos/datalad/datalad", "labels_url": "https://api.github.com/repos/datalad/datalad/issues/4063/labels{/name}", "comments_url": "https://api.github.com/repos/datalad/datalad/issues/4063/comments", "events_url": "https://api.github.com/repos/datalad/datalad/issues/4063/events", "html_url": "https://github.com/datalad/datalad/issues/4063", "id": 552653419, "node_id": "MDU6SXNzdWU1NTI2NTM0MTk=", "number": 4063, "title": "AnnexRepo.is_under_annex/file_has_content() broken", "user": {"login": "mih", "id": 136479, "node_id": "MDQ6VXNlcjEzNjQ3OQ==", "avatar_url": "https://avatars.githubusercontent.com/u/136479?v=4", "gravatar_id": "", "url": "https://api.github.com/users/mih", "html_url": "https://github.com/mih", "followers_url": "https://api.github.com/users/mih/followers", "following_url": "https://api.github.com/users/mih/following{/other_user}", "gists_url": "https://api.github.com/users/mih/gists{/gist_id}", "starred_url": "https://api.github.com/users/mih/starred{/owner}{/repo}", "subscriptions_url": "https://api.github.com/users/mih/subscriptions", "organizations_url": "https://api.github.com/users/mih/orgs", "repos_url": "https://api.github.com/users/mih/repos", "events_url": "https://api.github.com/users/mih/events{/privacy}", "received_events_url": "https://api.github.com/users/mih/received_events", "type": "User", "site_admin": false}, "labels": [{"id": 1757223715, "node_id": "MDU6TGFiZWwxNzU3MjIzNzE1", "url": "https://api.github.com/repos/datalad/datalad/labels/adjusted-branches", "name": "adjusted-branches", "color": "0052cc", "default": false, "description": "Issues caused by or affected adjusted branch operation"}, {"id": 1782622781, "node_id": "MDU6TGFiZWwxNzgyNjIyNzgx", "url": "https://api.github.com/repos/datalad/datalad/labels/severity-important", "name": "severity-important", "color": "cc0000", "default": false, "description": "major effect on the usability of a package, without rendering it completely unusable to everyone"}], "state": "closed", "locked": false, "assignee": null, "assignees": [], "milestone": null, "comments": 1, "created_at": "2020-01-21T06:36:41Z", "updated_at": "2020-01-21T07:37:01Z", "closed_at": "2020-01-21T07:37:01Z", "author_association": "MEMBER", "active_lock_reason": null, "body": "Their default \"quick\" check assumes locked mode, and is, as such, invalid with managed branches. Both methods are already frowned upon #3333. It might be time for them to die. Sadly, they are still being used (see below) and we can consider related functionality broken with managed branched too:\r\n\r\n#### is_under_annex\r\n\r\n- `download_url`\r\n- `add_archive_content`\r\n- `auto.py`\r\n- `ls`\r\n- `metadata`\r\n- `export_archive`\r\n- `AnnexRepo.add_url_to_file`\r\n- `GitRepo` and `AnnexRepo` tests\r\n\r\n#### file_has_content\r\n\r\n- `add_archive_content`\r\n- `auto.py`\r\n- `ls`\r\n- `metadata`\r\n- `aggregate`\r\n- `export_archive`\r\n- `ok_annex_get()` test helper\r\n\r\n", "closed_by": {"login": "mih", "id": 136479, "node_id": "MDQ6VXNlcjEzNjQ3OQ==", "avatar_url": "https://avatars.githubusercontent.com/u/136479?v=4", "gravatar_id": "", "url": "https://api.github.com/users/mih", "html_url": "https://github.com/mih", "followers_url": "https://api.github.com/users/mih/followers", "following_url": "https://api.github.com/users/mih/following{/other_user}", "gists_url": "https://api.github.com/users/mih/gists{/gist_id}", "starred_url": "https://api.github.com/users/mih/starred{/owner}{/repo}", "subscriptions_url": "https://api.github.com/users/mih/subscriptions", "organizations_url": "https://api.github.com/users/mih/orgs", "repos_url": "https://api.github.com/users/mih/repos", "events_url": "https://api.github.com/users/mih/events{/privacy}", "received_events_url": "https://api.github.com/users/mih/received_events", "type": "User", "site_admin": false}, "reactions": {"url": "https://api.github.com/repos/datalad/datalad/issues/4063/reactions", "total_count": 0, "+1": 0, "-1": 0, "laugh": 0, "hooray": 0, "confused": 0, "heart": 0, "rocket": 0, "eyes": 0}, "timeline_url": "https://api.github.com/repos/datalad/datalad/issues/4063/timeline", "performed_via_github_app": null}